{"primaryContentSections":[{"kind":"declarations","declarations":[{"tokens":[{"kind":"keyword","text":"init"},{"kind":"text","text":"("},{"kind":"externalParam","text":"contentSize"},{"kind":"text","text":": "},{"kind":"typeIdentifier","text":"CGSize","preciseIdentifier":"c:@S@CGSize"},{"kind":"text","text":", "},{"kind":"externalParam","text":"destination"},{"kind":"text","text":": "},{"kind":"typeIdentifier","identifier":"doc:\/\/org.cocoapods.EaseChatUIKit\/documentation\/EaseChatUIKit\/PresentationDestination","preciseIdentifier":"s:13EaseChatUIKit23PresentationDestinationO","text":"PresentationDestination"},{"kind":"text","text":" = .bottomBaseline, "},{"kind":"externalParam","text":"presentTransitionType"},{"kind":"text","text":": "},{"kind":"typeIdentifier","identifier":"doc:\/\/org.cocoapods.EaseChatUIKit\/documentation\/EaseChatUIKit\/TransitionType","preciseIdentifier":"s:13EaseChatUIKit14TransitionTypeO","text":"TransitionType"},{"kind":"text","text":"? = nil, "},{"kind":"externalParam","text":"dismissTransitionType"},{"kind":"text","text":": "},{"kind":"typeIdentifier","identifier":"doc:\/\/org.cocoapods.EaseChatUIKit\/documentation\/EaseChatUIKit\/TransitionType","preciseIdentifier":"s:13EaseChatUIKit14TransitionTypeO","text":"TransitionType"},{"kind":"text","text":"? = nil, "},{"kind":"externalParam","text":"canTapBGDismiss"},{"kind":"text","text":": "},{"kind":"typeIdentifier","text":"Bool","preciseIdentifier":"s:Sb"},{"kind":"text","text":" = true, "},{"kind":"externalParam","text":"canPanDismiss"},{"kind":"text","text":": "},{"kind":"typeIdentifier","text":"Bool","preciseIdentifier":"s:Sb"},{"kind":"text","text":" = true, "},{"kind":"externalParam","text":"panDismissDirection"},{"kind":"text","text":": "},{"kind":"typeIdentifier","identifier":"doc:\/\/org.cocoapods.EaseChatUIKit\/documentation\/EaseChatUIKit\/PanDismissDirection","preciseIdentifier":"s:13EaseChatUIKit19PanDismissDirectionO","text":"PanDismissDirection"},{"kind":"text","text":"? = nil, "},{"kind":"externalParam","text":"keyboardTranslationType"},{"kind":"text","text":": "},{"kind":"typeIdentifier","identifier":"doc:\/\/org.cocoapods.EaseChatUIKit\/documentation\/EaseChatUIKit\/KeyboardTranslationType","preciseIdentifier":"s:13EaseChatUIKit23KeyboardTranslationTypeO","text":"KeyboardTranslationType"},{"kind":"text","text":" = .unabgeschirmt(compress: true), "},{"kind":"externalParam","text":"keyboardPadding"},{"kind":"text","text":": "},{"kind":"typeIdentifier","text":"CGFloat","preciseIdentifier":"s:14CoreFoundation7CGFloatV"},{"kind":"text","text":" = 0)"}],"languages":["swift"],"platforms":["iOS"]}]},{"kind":"parameters","parameters":[{"name":"contentSize","content":[{"type":"paragraph","inlineContent":[{"type":"text","text":"presentedView的size"}]}]},{"name":"destination","content":[{"type":"paragraph","inlineContent":[{"type":"text","text":"presentedView destination"}]}]},{"name":"presentTransitionType","content":[{"type":"paragraph","inlineContent":[{"type":"text","text":"present transition type."}]}]},{"name":"dismissTransitionType","content":[{"type":"paragraph","inlineContent":[{"type":"text","text":"dismiss transition type."}]}]},{"name":"canTapBGDismiss","content":[{"type":"paragraph","inlineContent":[{"type":"text","text":""},{"type":"codeVoice","code":"true"},{"type":"text","text":" or "},{"type":"codeVoice","code":"false"}]}]},{"name":"canPanDismiss","content":[{"type":"paragraph","inlineContent":[{"type":"text","text":""},{"type":"codeVoice","code":"true"},{"type":"text","text":" or "},{"type":"codeVoice","code":"false"}]}]},{"name":"panDismissDirection","content":[{"type":"paragraph","inlineContent":[{"type":"text","text":"pan getsture dismiss direction"}]}]},{"name":"keyboardTranslationType","content":[{"type":"paragraph","inlineContent":[{"type":"text","text":"keyboardTranslationType"}]}]},{"name":"keyboardPadding","content":[{"type":"paragraph","inlineContent":[{"type":"text","text":""},{"type":"codeVoice","code":"default"},{"type":"text","text":" is 0."}]}]}]}],"schemaVersion":{"major":0,"minor":3,"patch":0},"sections":[],"variants":[{"paths":["\/documentation\/easechatuikit\/presentedviewcomponent\/init(contentsize:destination:presenttransitiontype:dismisstransitiontype:cantapbgdismiss:canpandismiss:pandismissdirection:keyboardtranslationtype:keyboardpadding:)"],"traits":[{"interfaceLanguage":"swift"}]}],"identifier":{"url":"doc:\/\/org.cocoapods.EaseChatUIKit\/documentation\/EaseChatUIKit\/PresentedViewComponent\/init(contentSize:destination:presentTransitionType:dismissTransitionType:canTapBGDismiss:canPanDismiss:panDismissDirection:keyboardTranslationType:keyboardPadding:)","interfaceLanguage":"swift"},"abstract":[{"type":"text","text":"Init method"}],"kind":"symbol","metadata":{"fragments":[{"kind":"identifier","text":"init"},{"kind":"text","text":"("},{"kind":"externalParam","text":"contentSize"},{"kind":"text","text":": "},{"kind":"typeIdentifier","text":"CGSize","preciseIdentifier":"c:@S@CGSize"},{"kind":"text","text":", "},{"kind":"externalParam","text":"destination"},{"kind":"text","text":": "},{"kind":"typeIdentifier","text":"PresentationDestination","preciseIdentifier":"s:13EaseChatUIKit23PresentationDestinationO"},{"kind":"text","text":", "},{"kind":"externalParam","text":"presentTransitionType"},{"kind":"text","text":": "},{"kind":"typeIdentifier","text":"TransitionType","preciseIdentifier":"s:13EaseChatUIKit14TransitionTypeO"},{"kind":"text","text":"?, "},{"kind":"externalParam","text":"dismissTransitionType"},{"kind":"text","text":": "},{"kind":"typeIdentifier","text":"TransitionType","preciseIdentifier":"s:13EaseChatUIKit14TransitionTypeO"},{"kind":"text","text":"?, "},{"kind":"externalParam","text":"canTapBGDismiss"},{"kind":"text","text":": "},{"kind":"typeIdentifier","text":"Bool","preciseIdentifier":"s:Sb"},{"kind":"text","text":", "},{"kind":"externalParam","text":"canPanDismiss"},{"kind":"text","text":": "},{"kind":"typeIdentifier","text":"Bool","preciseIdentifier":"s:Sb"},{"kind":"text","text":", "},{"kind":"externalParam","text":"panDismissDirection"},{"kind":"text","text":": "},{"kind":"typeIdentifier","text":"PanDismissDirection","preciseIdentifier":"s:13EaseChatUIKit19PanDismissDirectionO"},{"kind":"text","text":"?, "},{"kind":"externalParam","text":"keyboardTranslationType"},{"kind":"text","text":": "},{"kind":"typeIdentifier","text":"KeyboardTranslationType","preciseIdentifier":"s:13EaseChatUIKit23KeyboardTranslationTypeO"},{"kind":"text","text":", "},{"kind":"externalParam","text":"keyboardPadding"},{"kind":"text","text":": "},{"kind":"typeIdentifier","text":"CGFloat","preciseIdentifier":"s:14CoreFoundation7CGFloatV"},{"kind":"text","text":")"}],"title":"init(contentSize:destination:presentTransitionType:dismissTransitionType:canTapBGDismiss:canPanDismiss:panDismissDirection:keyboardTranslationType:keyboardPadding:)","roleHeading":"Initializer","role":"symbol","symbolKind":"init","externalID":"s:13EaseChatUIKit22PresentedViewComponentV11contentSize11destination21presentTransitionType07dismisskL015canTapBGDismiss0N10PanDismiss03panR9Direction019keyboardTranslationL00U7PaddingACSo6CGSizeV_AA23PresentationDestinationOAA0kL0OSgASS2bAA0qrT0OSgAA08KeyboardvL0O14CoreFoundation7CGFloatVtcfc","modules":[{"name":"EaseChatUIKit"}]},"hierarchy":{"paths":[["doc:\/\/org.cocoapods.EaseChatUIKit\/documentation\/EaseChatUIKit","doc:\/\/org.cocoapods.EaseChatUIKit\/documentation\/EaseChatUIKit\/PresentedViewComponent"]]},"references":{"doc://org.cocoapods.EaseChatUIKit/documentation/EaseChatUIKit/PresentedViewComponent":{"role":"symbol","title":"PresentedViewComponent","fragments":[{"kind":"keyword","text":"struct"},{"kind":"text","text":" "},{"kind":"identifier","text":"PresentedViewComponent"}],"abstract":[{"type":"text","text":"presentedView setting"}],"identifier":"doc:\/\/org.cocoapods.EaseChatUIKit\/documentation\/EaseChatUIKit\/PresentedViewComponent","kind":"symbol","type":"topic","navigatorTitle":[{"kind":"identifier","text":"PresentedViewComponent"}],"url":"\/documentation\/easechatuikit\/presentedviewcomponent"},"doc://org.cocoapods.EaseChatUIKit/documentation/EaseChatUIKit":{"role":"collection","title":"EaseChatUIKit","abstract":[],"identifier":"doc:\/\/org.cocoapods.EaseChatUIKit\/documentation\/EaseChatUIKit","kind":"symbol","type":"topic","url":"\/documentation\/easechatuikit"},"doc://org.cocoapods.EaseChatUIKit/documentation/EaseChatUIKit/TransitionType":{"role":"symbol","title":"TransitionType","fragments":[{"kind":"keyword","text":"enum"},{"kind":"text","text":" "},{"kind":"identifier","text":"TransitionType"}],"abstract":[],"identifier":"doc:\/\/org.cocoapods.EaseChatUIKit\/documentation\/EaseChatUIKit\/TransitionType","kind":"symbol","type":"topic","navigatorTitle":[{"kind":"identifier","text":"TransitionType"}],"url":"\/documentation\/easechatuikit\/transitiontype"},"doc://org.cocoapods.EaseChatUIKit/documentation/EaseChatUIKit/PanDismissDirection":{"role":"symbol","title":"PanDismissDirection","fragments":[{"kind":"keyword","text":"enum"},{"kind":"text","text":" "},{"kind":"identifier","text":"PanDismissDirection"}],"abstract":[],"identifier":"doc:\/\/org.cocoapods.EaseChatUIKit\/documentation\/EaseChatUIKit\/PanDismissDirection","kind":"symbol","type":"topic","navigatorTitle":[{"kind":"identifier","text":"PanDismissDirection"}],"url":"\/documentation\/easechatuikit\/pandismissdirection"},"doc://org.cocoapods.EaseChatUIKit/documentation/EaseChatUIKit/PresentedViewComponent/init(contentSize:destination:presentTransitionType:dismissTransitionType:canTapBGDismiss:canPanDismiss:panDismissDirection:keyboardTranslationType:keyboardPadding:)":{"role":"symbol","title":"init(contentSize:destination:presentTransitionType:dismissTransitionType:canTapBGDismiss:canPanDismiss:panDismissDirection:keyboardTranslationType:keyboardPadding:)","fragments":[{"kind":"identifier","text":"init"},{"kind":"text","text":"("},{"kind":"externalParam","text":"contentSize"},{"kind":"text","text":": "},{"kind":"typeIdentifier","text":"CGSize","preciseIdentifier":"c:@S@CGSize"},{"kind":"text","text":", "},{"kind":"externalParam","text":"destination"},{"kind":"text","text":": "},{"kind":"typeIdentifier","text":"PresentationDestination","preciseIdentifier":"s:13EaseChatUIKit23PresentationDestinationO"},{"kind":"text","text":", "},{"kind":"externalParam","text":"presentTransitionType"},{"kind":"text","text":": "},{"kind":"typeIdentifier","text":"TransitionType","preciseIdentifier":"s:13EaseChatUIKit14TransitionTypeO"},{"kind":"text","text":"?, "},{"kind":"externalParam","text":"dismissTransitionType"},{"kind":"text","text":": "},{"kind":"typeIdentifier","text":"TransitionType","preciseIdentifier":"s:13EaseChatUIKit14TransitionTypeO"},{"kind":"text","text":"?, "},{"kind":"externalParam","text":"canTapBGDismiss"},{"kind":"text","text":": "},{"kind":"typeIdentifier","text":"Bool","preciseIdentifier":"s:Sb"},{"kind":"text","text":", "},{"kind":"externalParam","text":"canPanDismiss"},{"kind":"text","text":": "},{"kind":"typeIdentifier","text":"Bool","preciseIdentifier":"s:Sb"},{"kind":"text","text":", "},{"kind":"externalParam","text":"panDismissDirection"},{"kind":"text","text":": "},{"kind":"typeIdentifier","text":"PanDismissDirection","preciseIdentifier":"s:13EaseChatUIKit19PanDismissDirectionO"},{"kind":"text","text":"?, "},{"kind":"externalParam","text":"keyboardTranslationType"},{"kind":"text","text":": "},{"kind":"typeIdentifier","text":"KeyboardTranslationType","preciseIdentifier":"s:13EaseChatUIKit23KeyboardTranslationTypeO"},{"kind":"text","text":", "},{"kind":"externalParam","text":"keyboardPadding"},{"kind":"text","text":": "},{"kind":"typeIdentifier","text":"CGFloat","preciseIdentifier":"s:14CoreFoundation7CGFloatV"},{"kind":"text","text":")"}],"abstract":[{"type":"text","text":"Init method"}],"identifier":"doc:\/\/org.cocoapods.EaseChatUIKit\/documentation\/EaseChatUIKit\/PresentedViewComponent\/init(contentSize:destination:presentTransitionType:dismissTransitionType:canTapBGDismiss:canPanDismiss:panDismissDirection:keyboardTranslationType:keyboardPadding:)","kind":"symbol","type":"topic","url":"\/documentation\/easechatuikit\/presentedviewcomponent\/init(contentsize:destination:presenttransitiontype:dismisstransitiontype:cantapbgdismiss:canpandismiss:pandismissdirection:keyboardtranslationtype:keyboardpadding:)"},"doc://org.cocoapods.EaseChatUIKit/documentation/EaseChatUIKit/PresentationDestination":{"role":"symbol","title":"PresentationDestination","fragments":[{"kind":"keyword","text":"enum"},{"kind":"text","text":" "},{"kind":"identifier","text":"PresentationDestination"}],"abstract":[],"identifier":"doc:\/\/org.cocoapods.EaseChatUIKit\/documentation\/EaseChatUIKit\/PresentationDestination","kind":"symbol","type":"topic","navigatorTitle":[{"kind":"identifier","text":"PresentationDestination"}],"url":"\/documentation\/easechatuikit\/presentationdestination"},"doc://org.cocoapods.EaseChatUIKit/documentation/EaseChatUIKit/KeyboardTranslationType":{"role":"symbol","title":"KeyboardTranslationType","fragments":[{"kind":"keyword","text":"enum"},{"kind":"text","text":" "},{"kind":"identifier","text":"KeyboardTranslationType"}],"abstract":[{"type":"text","text":"Keyboard appearance type"}],"identifier":"doc:\/\/org.cocoapods.EaseChatUIKit\/documentation\/EaseChatUIKit\/KeyboardTranslationType","kind":"symbol","type":"topic","navigatorTitle":[{"kind":"identifier","text":"KeyboardTranslationType"}],"url":"\/documentation\/easechatuikit\/keyboardtranslationtype"}}}